{"cameraMode":{"drawMode":0,"name":"Shaded","section":"Shading Mode"},"sceneLighting":false,"audioPlay":false,"sceneViewState":{"showFog":true,"showMaterialUpdate":false,"showSkybox":false,"showFlares":true,"showImageEffects":true,"showParticleSystems":true},"in2DMode":false,"pivot":{"x":1.347995638847351,"y":0.2989116907119751,"z":-7.8274431228637699},"rotation":{"x":0.2669066786766052,"y":-0.14292047917842866,"z":0.0403871014714241,"w":0.9523164629936218},"size":0.7215141654014587,"orthographic":false}